GroupMeAPI/__init__.py
GroupMeAPI/bot.py
GroupMeAPI/dm.py
GroupMeAPI/group.py
GroupMeAPI/user.py
python_groupmeapi-1.0.0.dist-info/LICENSE
python_groupmeapi-1.0.0.dist-info/METADATA
python_groupmeapi-1.0.0.dist-info/WHEEL
python_groupmeapi-1.0.0.dist-info/top_level.txt
python_groupmeapi-1.0.0.dist-info/RECORD
