Metadata-Version: 2.1
Name: python-groupmeapi
Version: 1.0.0
Summary: An API wrapper for GroupMe
Author: LL
Keywords: api,groupme,wrapper
Classifier: License :: OSI Approved :: GNU General Public License v3 or later (GPLv3+)
Classifier: Programming Language :: Python
Classifier: Programming Language :: Python :: 3
Requires-Python: >=3.7
License-File: LICENSE
